{"trial_id": "3a78712a3f5ef121d2e859d00ac079bd", "hyperparameters": {"space": [{"class_name": "Int", "config": {"name": "num_layers", "default": null, "conditions": [], "min_value": 1, "max_value": 4, "step": 1, "sampling": null}}, {"class_name": "Int", "config": {"name": "units_0", "default": null, "conditions": [], "min_value": 200, "max_value": 800, "step": 100, "sampling": null}}, {"class_name": "Int", "config": {"name": "units_1", "default": null, "conditions": [], "min_value": 200, "max_value": 800, "step": 100, "sampling": null}}, {"class_name": "Int", "config": {"name": "units_2", "default": null, "conditions": [], "min_value": 200, "max_value": 800, "step": 100, "sampling": null}}, {"class_name": "Int", "config": {"name": "units_3", "default": null, "conditions": [], "min_value": 200, "max_value": 800, "step": 100, "sampling": null}}], "values": {"num_layers": 4, "units_0": 300, "units_1": 500, "units_2": 700, "units_3": 700}}, "metrics": {"metrics": {"loss": {"direction": "min", "observations": [{"value": [0.003156352322548628], "step": 0}]}, "val_loss": {"direction": "min", "observations": [{"value": [0.0023401903842265406], "step": 0}]}}}, "score": 0.0023401903842265406, "best_step": 0, "status": "COMPLETED"}